fk/__init__.py
fk-0.0.9.dist-info/licenses/LICENSE
fk-0.0.9.dist-info/METADATA
fk-0.0.9.dist-info/WHEEL
fk-0.0.9.dist-info/top_level.txt
fk-0.0.9.dist-info/RECORD
