Metadata-Version: 2.4
Name: fk
Version: 0.0.9
Summary: FactKit - managing and querying simple factual knowledge bases
Home-page: https://github.com/lyricalgrin/fk
License: apache-2.0
Platform: any
License-File: LICENSE
Requires-Dist: dol
Requires-Dist: pandas
Dynamic: license-file
